pykart.py
pykart-0.0.4.dist-info/LICENSE.txt
pykart-0.0.4.dist-info/METADATA
pykart-0.0.4.dist-info/WHEEL
pykart-0.0.4.dist-info/top_level.txt
pykart-0.0.4.dist-info/RECORD
