Metadata-Version: 2.1
Name: pykart
Version: 0.0.4
Summary: pykart is module which help to fetch product-data from ecommerce website [flipkart]
Home-page: https://github.com/broxmapyo007/pykart
Author: Adesh Dangi
Author-email: adeshdangi104@gmail.com
License: UNKNOWN
Platform: UNKNOWN
Classifier: Programming Language :: Python :: 3.6
Classifier: Programming Language :: Python :: 3.7
Classifier: License :: OSI Approved :: GNU General Public License v3 or later (GPLv3+)
Classifier: Operating System :: OS Independent
Requires-Dist: requests
Requires-Dist: bs4
Requires-Dist: prettytable
Requires-Dist: lxml
